LICENSE.txt
MANIFEST.in
README.md
README.rst
setup.py
timeseries_example.py
optml/__init__.py
optml/ant_colony_optimizer.py
optml/genetic_optimizer.py
optml/gridsearch_optimizer.py
optml/hyperopt_optimizer.py
optml/models.py
optml/optimizer_base.py
optml/random_search.py
optml/smac_optimizer.py
optml/util.py
optml/wrappers.py
optml.egg-info/PKG-INFO
optml.egg-info/SOURCES.txt
optml.egg-info/dependency_links.txt
optml.egg-info/requires.txt
optml.egg-info/top_level.txt
optml/bayesian_optimizer/__init__.py
optml/bayesian_optimizer/bayesianoptimizer.py
optml/bayesian_optimizer/gp_categorical.py
optml/bayesian_optimizer/kernels.py
optml/bayesian_optimizer/optimizers.py