Metadata-Version: 1.1
Name: optml
Version: 0.2.3
Summary: A library for hyperparameter optimization of ML models
Home-page: https://github.com/johannespetrat/OptML
Author: Johannes Petrat
Author-email: petrat.johannes@gmail.com
License: MIT
Keywords: optimization machine learning hyperparameter bayesian gridsearch
Platform: UNKNOWN
Classifier: Development Status :: 3 - Alpha
Classifier: Intended Audience :: Developers
Classifier: Topic :: Software Development :: Build Tools
Classifier: License :: OSI Approved :: MIT License
Classifier: Programming Language :: Python :: 2
Classifier: Programming Language :: Python :: 2.7
Classifier: Programming Language :: Python :: 3
Classifier: Programming Language :: Python :: 3.3
Classifier: Programming Language :: Python :: 3.4
Classifier: Programming Language :: Python :: 3.5
